<?xml version="1.0" encoding="UTF-8" standalone="yes"?>
<items>



<item>
<title>[COLOR silver][B]Sonic 3: O Filme[/B][/COLOR][COLOR yellow] FULL HD[/COLOR]</title>
<link>plugin://plugin.video.elementum/play?uri=magnet:?xt=urn:btih:72B1E0970A99F4053A010AD66D86A136E3C66547&dn=HIDRATORRENTS.ORG.-MAGNET-LINK.MKV.Sonic.3.O.Filme.2024.1080p.WEB-DL.DUAL.5.1&tr=udp%3a%2f%2ftracker.openbittorrent.com%3a80%2fannounce&tr=udp%3a%2f%2ftracker.publicbt.com%3a80%2fannounce&tr=udp%3a%2f%2ftracker.ccc.de%3a80%2fannounce&tr=wss%3a%2f%2fwstracker.online$$lsname=[COLOR white]Sonic 3: O Filme - FILME[/COLOR]</link>
<link>plugin://plugin.video.resolverurl_player?url=https://dropload.io/2chc9lwqrl1s$$lsname=[COLOR aquamarine]TRAILER[/COLOR]</link>
<thumbnail>https://image.tmdb.org/t/p/w500/tfM1T6tAivjvy0sLwt6Y9WvlmzB.jpg</thumbnail>
<fanart>https://image.tmdb.org/t/p/w1280/zOpe0eHsq0A2NvNyBbtT6sj53qV.jpg</fanart>
<info>
[COLOR red]Título Original:[/COLOR] Sonic the Hedgehog 3
[COLOR yellow]Ano:[/COLOR] 2024
[COLOR red]Nota:[/COLOR] 7.8
[COLOR yellow]Gênero:[/COLOR] Ação, Ficção Científica, Comédia, Família, Aventura, Fantasia
[COLOR red]Sinopse:[/COLOR] Sonic, Knuckles e Tails se reúnem contra um novo e poderoso adversário, Shadow, um vilão misterioso com poderes diferentes de tudo que eles já enfrentaram antes. Com suas habilidades superadas em todos os sentidos, a Equipe Sonic deve buscar uma aliança improvável na esperança de parar Shadow e proteger o planeta.
</info>
</item>

<item>
    <title>[B][COLOR red]ZENSHU 1ª Temporada - (2025)[/COLOR][/B] - [COLOR orange]IMDb: 7.8[/COLOR] [COLOR red]+16[/COLOR]</title>
    <link>magnet:?xt=urn:btih:a57ca9bc6552e0670c3786ef96eb5aa701280792$nome=[COLOR blue]Série - ZENSHU 1ª Temporada Ep.01 (2025)[/COLOR]</link>
    <link>magnet:?xt=urn:btih:6d406362aaec97e6fb348345cd56b158e00245f0$nome=[COLOR yellow]Série - ZENSHU 1ª Temporada Ep.02 (2025)[/COLOR]</link>
    <link>magnet:?xt=urn:btih:19cc5f21d4e7fb471e6621b351424b79f9df0ab6$nome=[COLOR blue]Série - ZENSHU 1ª Temporada Ep.03 (2025)[/COLOR]</link>
    <link>magnet:?xt=urn:btih:3dd21883f212a9ce05498e51caa110fa08bbbf24$nome=[COLOR yellow]Série - ZENSHU 1ª Temporada Ep.04 (2025)[/COLOR]</link>
    <link>plugin://plugin.video.youtube/play/?video_id=xwufQyREisw$nome=[COLOR blue]Trailer - ZENSHU 1ª Temporada (2025)[/COLOR]</link>
    <thumbnail>https://image.tmdb.org/t/p/original/vxVg6gyuyM2hmdXQwbNmNtdsuyD.jpg</thumbnail>
    <fanart>https://image.tmdb.org/t/p/original/Apy6SEE54GxMbUIYo7Hpo3Dr718.jpg</fanart>
    <genre>Animação, Drama</genre>
    <info>
        [COLOR red]Título Original:[/COLOR] ZENSHU
        [COLOR orange]Direção:[/COLOR] Naoko Yamada
        [COLOR red]Ano:[/COLOR] 2025
        [COLOR orange]Duração:[/COLOR] Episódios de 24 min
        [COLOR red]Classificação Indicativa:[/COLOR] 16 anos
        [COLOR orange]Nota IMDb:[/COLOR] 7.8
        [COLOR red]Gêneros:[/COLOR] Animação, Drama
        [COLOR orange]Sinopse:[/COLOR] Depois de se formar no ensino médio, Natsuko Hirose começa sua carreira como animadora. Seu talento logo se destaca e, em pouco tempo, ela faz sua estreia como diretora. Seu primeiro anime torna-se um sucesso estrondoso, provocando um fenômeno social e fazendo com que ela seja reconhecida como uma diretora prodígio em ascensão. Seu próximo projeto é um filme de comédia romântica centrado no tema do primeiro amor. No entanto, como nunca se apaixonou, Natsuko tem dificuldade em entender o conceito, o que a impede de criar o storyboard e interrompe completamente a produção do filme.
        [COLOR red]Elenco Principal:[/COLOR]
        [COLOR orange]Kana Hanazawa[/COLOR]
        [COLOR orange]Mamoru Miyano[/COLOR]
        [COLOR orange]Saori Hayami[/COLOR]
        [COLOR orange]Hiroshi Kamiya[/COLOR]
    </info>
</item>


<item>
<title>A Era do Gelo 4</title>
<year>2012</year>
<genre>Animação, Comédia, Aventura, Família</genre>
<thumbnail>https://image.tmdb.org/t/p/original/dWiHLqARtyAAOy0nLvXIxRYkfNA.jpg</thumbnail>
<fanart>https://image.tmdb.org/t/p/original/kyTlMMVWo1GffYoQctZwLqJcwaj.jpg</fanart>
<link>https://1a-1791.com/video/fwe2/9a/s8/2/y/7/w/d/y7wdw.gaa.mp4</link>
<info>Sempre em busca de sua cobiçada noz, o esquilo Scrat provoca, sem querer, a separação dos continentes. A situação causa mudanças no terreno de vários locais, entre eles onde os amigos Manny, Diego e Sid estão alojados. Um terremoto faz com que o trio fique preso em um iceberg.</info>
</item>


</items>
