<?xml version="1.0" encoding="UTF-8" standalone="yes"?>
<items>


    
<title>[COLOR silver][B]The Mountain Within Me[/B][/COLOR][COLOR yellow] FULL HD[/COLOR]</title>
<link>plugin://plugin.video.elementum/play?uri=The Mountain Within Me$$lsname=[COLOR white]The Mountain Within Me - FILME[/COLOR]</link>
<thumbnail>https://image.tmdb.org/t/p/w500/mRwlV2K8RKj9bJxPqVmEtjd1zAC.jpg</thumbnail>
<fanart>https://image.tmdb.org/t/p/w1280/310EbteoLeSxB97xONW1GLkbpS7.jpg</fanart>
<info>
[COLOR yellow]Título Original:[/COLOR] The Mountain Within Me
[COLOR yellow]Ano:[/COLOR] 2024
[COLOR yellow]Nota:[/COLOR] 7
[COLOR yellow]Gênero:[/COLOR] Documentário
[COLOR yellow]Sinopse:[/COLOR] Depois de sofrer uma lesão catastrófica e quase fatal na medula espinhal, o mundo do jogador profissional de rugby Ed Jackson mudou para sempre. THE MOUNTAIN WITHIN ME acompanha a jornada de Ed em sua recuperação enquanto ele encara os desafios físicos e mentais de Snowdonia, dos Alpes e do Himalaia, para os desafios que mudam sua vida perto de casa.
</info>
</item>

<item>
<title>A Era do Gelo 4</title>
<year>2012</year>
<genre>Animação, Comédia, Aventura, Família</genre>
<thumbnail>https://image.tmdb.org/t/p/original/dWiHLqARtyAAOy0nLvXIxRYkfNA.jpg</thumbnail>
<fanart>https://image.tmdb.org/t/p/original/kyTlMMVWo1GffYoQctZwLqJcwaj.jpg</fanart>
<link>https://1a-1791.com/video/fwe2/9a/s8/2/y/7/w/d/y7wdw.gaa.mp4</link>
<info>Sempre em busca de sua cobiçada noz, o esquilo Scrat provoca, sem querer, a separação dos continentes. A situação causa mudanças no terreno de vários locais, entre eles onde os amigos Manny, Diego e Sid estão alojados. Um terremoto faz com que o trio fique preso em um iceberg.</info>
</item>


</items>
